model_container.i
setup.py
model_container/__cbi__.py
model_container/__init__.py
model_container/errors.py
model_container/model_container_base.py
model_container/symbols.py
model_container.egg-info/PKG-INFO
model_container.egg-info/SOURCES.txt
model_container.egg-info/dependency_links.txt
model_container.egg-info/top_level.txt