Metadata-Version: 1.0
Name: model-container
Version: 0.0.0-alpha
Summary: The Model Container is used as an abstraction layer on top of a simulator and deals with biological entities and end-user concepts instead of mathematical equations.
Home-page: http://pypi.python.org/pypi/model-container
Author: Mando Rodriguez
Author-email: rodrigueza14@uthscsa.edu
License: GPL
Keywords: neuroscience neurosimulator simulator modeling GENESIS
Platform: Unix
Platform: Lunix
Platform: MacOS X
Classifier: Development Status :: 3 - Alpha
Classifier: Environment :: Console
Classifier: Intended Audience :: End Users/Desktop
Classifier: Intended Audience :: Developers
Classifier: Intended Audience :: Science/Research
Classifier: License :: OSI Approved :: GNU General Public License (GPL)
Classifier: Operating System :: MacOS :: MacOS X
Classifier: Operating System :: POSIX :: Linux
Classifier: Programming Language :: Python :: 2.5
Classifier: Programming Language :: Python :: 2.6
Classifier: Topic :: Software Development :: Libraries :: Python Modules
